ScrapingDSL-0.1.dist-info/METADATA
ScrapingDSL-0.1.dist-info/RECORD
ScrapingDSL-0.1.dist-info/WHEEL
ScrapingDSL-0.1.dist-info/top_level.txt
scraping_dsl/__init__.py
scraping_dsl/base_generator.py
scraping_dsl/execute.py
scraping_dsl/generate.py
scraping_dsl/generate_spider.py
scraping_dsl/root.py
